[
  {
    "ContainingType": "Course.Controllers.CoursesController",
    "Method": "Create",
    "RelativePath": "api/Courses",
    "HttpMethod": "POST",
    "IsController": true,
    "Order": 0,
    "Parameters": [
      {
        "Name": "req",
        "Type": "Course.Contracts.CreateCourseRequest",
        "IsRequired": true
      }
    ],
    "ReturnTypes": []
  },
  {
    "ContainingType": "Course.Controllers.CoursesController",
    "Method": "GetAll",
    "RelativePath": "api/Courses",
    "HttpMethod": "GET",
    "IsController": true,
    "Order": 0,
    "Parameters": [],
    "ReturnTypes": []
  },
  {
    "ContainingType": "Course.Controllers.CoursesController",
    "Method": "GetById",
    "RelativePath": "api/Courses/{id}",
    "HttpMethod": "GET",
    "IsController": true,
    "Order": 0,
    "Parameters": [
      {
        "Name": "id",
        "Type": "System.Guid",
        "IsRequired": true
      }
    ],
    "ReturnTypes": []
  }
]